[
  {
    "idFavori": "uax4b3ciqv",
    "intitule": "Ma recherche experte",
    "type": "Recherche experte",
    "createur": "adminsgg"
  },
  {
    "idFavori": "9zewtbva98",
    "intitule": "Ma recherche libre",
    "type": "Recherche libre",
    "createur": "adminsgg"
  },
  {
    "idFavori": "26cdr3pd36",
    "intitule": "Ma recherche experte",
    "type": "Modèles de feuille de route",
    "createur": "adminsgg"
  },
  {
    "idFavori": "84lphcv9uy",
    "intitule": "Ma recherche experte",
    "type": "Modèles de feuille de route",
    "createur": "adminsgg"
  },
  {
    "idFavori": "grv938iqes",
    "intitule": "Ma recherche experte",
    "type": "Modèles de feuille de route",
    "createur": "adminsgg"
  },
  {
    "idFavori": "zye1z6y6i1",
    "intitule": "Ma recherche experte",
    "type": "Modèles de feuille de route",
    "createur": "adminsgg"
  },
  {
    "idFavori": "33gx4syzt0",
    "intitule": "Ma recherche experte",
    "type": "Modèles de feuille de route",
    "createur": "adminsgg"
  },
  {
    "idFavori": "s0916145aq",
    "intitule": "Ma recherche experte",
    "type": "Modèles de feuille de route",
    "createur": "adminsgg"
  },
  {
    "idFavori": "2s377fry99",
    "intitule": "Ma recherche experte",
    "type": "Modèles de feuille de route",
    "createur": "adminsgg"
  },
  {
    "idFavori": "k6sz48sewa",
    "intitule": "Ma recherche experte",
    "type": "Modèles de feuille de route",
    "createur": "adminsgg"
  }
]